zz_tool/__init__.py
zz_tool/cli.py
putils_z-0.1.1.dist-info/METADATA
putils_z-0.1.1.dist-info/WHEEL
putils_z-0.1.1.dist-info/entry_points.txt
putils_z-0.1.1.dist-info/top_level.txt
putils_z-0.1.1.dist-info/RECORD
