Metadata-Version: 2.4
Name: putils-z
Version: 0.1.1
Summary: Utility CLI tool
Author: ubuntu
Requires-Python: >=3.6
Dynamic: author
Dynamic: requires-python
Dynamic: summary
